pdf_ocr_processor-2.0.3.dist-info/licenses/LICENSE
pdf_processor/__init__.py
pdf_processor/__main__.py
pdf_processor/__version__.py
pdf_processor/cli.py
pdf_processor/config/__init__.py
pdf_processor/config/settings.py
pdf_processor/models/__init__.py
pdf_processor/models/ocr_result.py
pdf_processor/models/retry_config.py
pdf_processor/processing/__init__.py
pdf_processor/processing/image_enhancement.py
pdf_processor/processing/ocr_processor.py
pdf_processor/processing/pdf_processor.py
pdf_processor/processing/svg_generator.py
pdf_processor/processing/ocr/__init__.py
pdf_processor/processing/ocr/batch_processor.py
pdf_processor/processing/ocr/models.py
pdf_processor/processing/ocr/ollama_client.py
pdf_processor/processing/ocr/result_parser.py
pdf_processor/processing/svg/__init__.py
pdf_processor/processing/svg/base_generator.py
pdf_processor/processing/svg/multipage_generator.py
pdf_processor/processing/svg/page_generator.py
pdf_processor/processing/svg/elements/__init__.py
pdf_processor/processing/svg/elements/image.py
pdf_processor/processing/svg/elements/navigation.py
pdf_processor/processing/svg/elements/text.py
pdf_processor/processing/svg/utils/__init__.py
pdf_processor/processing/svg/utils/style_utils.py
pdf_processor/processing/svg/utils/svg_utils.py
pdf_processor/utils/__init__.py
pdf_processor/utils/file_utils.py
pdf_processor/utils/logging_utils.py
pdf_processor/utils/validation_utils.py
tests/__init__.py
tests/conftest.py
tests/unit_tests.py
pdf_ocr_processor-2.0.3.dist-info/METADATA
pdf_ocr_processor-2.0.3.dist-info/WHEEL
pdf_ocr_processor-2.0.3.dist-info/entry_points.txt
pdf_ocr_processor-2.0.3.dist-info/top_level.txt
pdf_ocr_processor-2.0.3.dist-info/RECORD
