Metadata-Version: 2.4
Name: pdf-ocr-processor
Version: 2.0.3
Summary: Advanced PDF OCR processing with AI-powered text extraction and selectable text overlays
Home-page: https://github.com/your-repo/pdf-ocr-processor
Author: PDF OCR Processor Team
Author-email: PDF OCR Processor Team <team@pdf-ocr-processor.com>
License: Apache-2.0
Project-URL: Homepage, https://github.com/your-username/pdf-ocr-processor
Project-URL: Documentation, https://pdf-ocr-processor.readthedocs.io/
Project-URL: Repository, https://github.com/your-username/pdf-ocr-processor
Project-URL: Changelog, https://github.com/your-username/pdf-ocr-processor/blob/main/CHANGELOG.md
Project-URL: Bug Reports, https://github.com/your-username/pdf-ocr-processor/issues
Keywords: pdf,ocr,text-extraction,ai,ollama,document-processing,computer-vision
Classifier: Development Status :: 5 - Production/Stable
Classifier: Intended Audience :: Developers
Classifier: Intended Audience :: End Users/Desktop
Classifier: Intended Audience :: Science/Research
Classifier: License :: OSI Approved :: Apache Software License
Classifier: Operating System :: OS Independent
Classifier: Programming Language :: Python :: 3
Classifier: Programming Language :: Python :: 3.8
Classifier: Programming Language :: Python :: 3.9
Classifier: Programming Language :: Python :: 3.10
Classifier: Programming Language :: Python :: 3.11
Classifier: Programming Language :: Python :: 3.12
Classifier: Topic :: Scientific/Engineering :: Image Processing
Classifier: Topic :: Text Processing :: Markup
Classifier: Topic :: Multimedia :: Graphics :: Graphics Conversion
Classifier: Topic :: Utilities
Requires-Python: >=3.8
License-File: LICENSE
Requires-Dist: PyMuPDF>=1.23.0
Requires-Dist: Pillow>=10.0.0
Requires-Dist: requests>=2.31.0
Requires-Dist: pyyaml>=6.0.1
Requires-Dist: tqdm>=4.66.0
Requires-Dist: numpy>=1.24.0
Requires-Dist: opencv-python>=4.8.0
Requires-Dist: lxml>=4.9.0
Requires-Dist: python-dotenv>=1.0.0
Requires-Dist: pandas>=2.0.0
Requires-Dist: python-dateutil>=2.8.2
Requires-Dist: pytz>=2023.3
Requires-Dist: click>=8.1.0
Requires-Dist: rich>=13.4.0
Requires-Dist: loguru>=0.7.0
Provides-Extra: dev
Requires-Dist: pytest>=7.4.0; extra == "dev"
Requires-Dist: pytest-cov>=4.1.0; extra == "dev"
Requires-Dist: pytest-mock>=3.10.0; extra == "dev"
Requires-Dist: pytest-xdist>=3.3.0; extra == "dev"
Requires-Dist: black>=23.0.0; extra == "dev"
Requires-Dist: isort>=5.12.0; extra == "dev"
Requires-Dist: flake8>=6.0.0; extra == "dev"
Requires-Dist: mypy>=1.5.0; extra == "dev"
Requires-Dist: pre-commit>=3.3.0; extra == "dev"
Requires-Dist: pylint>=2.17.0; extra == "dev"
Requires-Dist: mypy-extensions>=1.0.0; extra == "dev"
Requires-Dist: sphinx>=7.0.0; extra == "dev"
Requires-Dist: sphinx-rtd-theme>=1.2.0; extra == "dev"
Requires-Dist: sphinx-autodoc-typehints>=1.24.0; extra == "dev"
Requires-Dist: myst-parser>=1.0.0; extra == "dev"
Provides-Extra: gpu
Requires-Dist: torch>=2.0.0; extra == "gpu"
Requires-Dist: torchvision>=0.15.0; extra == "gpu"
Requires-Dist: transformers>=4.30.0; extra == "gpu"
Requires-Dist: sentencepiece>=0.1.99; extra == "gpu"
Provides-Extra: web
Requires-Dist: fastapi>=0.100.0; extra == "web"
Requires-Dist: uvicorn>=0.23.0; extra == "web"
Requires-Dist: streamlit>=1.25.0; extra == "web"
Requires-Dist: python-multipart>=0.0.6; extra == "web"
Requires-Dist: python-jose[cryptography]>=3.3.0; extra == "web"
Dynamic: author
Dynamic: home-page
Dynamic: license-file
Dynamic: requires-python
